siren_pytorch/__init__.py
siren_pytorch/siren_pytorch.py
siren_pytorch-0.1.7.dist-info/LICENSE
siren_pytorch-0.1.7.dist-info/METADATA
siren_pytorch-0.1.7.dist-info/WHEEL
siren_pytorch-0.1.7.dist-info/top_level.txt
siren_pytorch-0.1.7.dist-info/RECORD
