Metadata-Version: 2.1
Name: siren-pytorch
Version: 0.1.7
Summary: Implicit Neural Representations with Periodic Activation Functions
Home-page: https://github.com/lucidrains/siren-pytorch
Author: Phil Wang
Author-email: lucidrains@gmail.com
License: MIT
Keywords: artificial intelligence,deep learning
Classifier: Development Status :: 4 - Beta
Classifier: Intended Audience :: Developers
Classifier: Topic :: Scientific/Engineering :: Artificial Intelligence
Classifier: License :: OSI Approved :: MIT License
Classifier: Programming Language :: Python :: 3.6
License-File: LICENSE
Requires-Dist: einops
Requires-Dist: torch
